tornado_async_transformer/__init__.py
tornado_async_transformer/helpers.py
tornado_async_transformer/py.typed
tornado_async_transformer/tool.py
tornado_async_transformer/tornado_async_transformer.py
tornado_async_transformer-0.2.0.dist-info/METADATA
tornado_async_transformer-0.2.0.dist-info/WHEEL
tornado_async_transformer-0.2.0.dist-info/top_level.txt
tornado_async_transformer-0.2.0.dist-info/RECORD
