Metadata-Version: 2.1
Name: tornado-async-transformer
Version: 0.2.0
Summary: libcst transformer and codemod for updating tornado @gen.coroutine syntax to python3.5+ native async/await
Home-page: https://github.com/zhammer/tornado-async-transformer
Author: Zach Hammer
Author-email: zachary_hammer@alumni.brown.edu
License: MIT License
Platform: UNKNOWN
Classifier: License :: OSI Approved :: MIT License
Classifier: Topic :: Software Development :: Libraries
Classifier: Programming Language :: Python :: 3.6
Classifier: Programming Language :: Python :: 3.7
Requires-Dist: libcst (==0.1.2)
